cherab_imas.dylibs/libomp.dylib
cherab_imas-0.3.0.dist-info/RECORD
cherab_imas-0.3.0.dist-info/WHEEL
cherab_imas-0.3.0.dist-info/METADATA
cherab_imas-0.3.0.dist-info/licenses/LICENCE.txt
cherab/__init__.pxd
cherab/imas/__init__.py
cherab/imas/plasma/blend.py
cherab/imas/plasma/equilibrium.py
cherab/imas/plasma/edge.py
cherab/imas/plasma/utility.py
cherab/imas/plasma/__init__.py
cherab/imas/plasma/core.py
cherab/imas/ggd/base_mesh.py
cherab/imas/ggd/unstruct_2d_mesh.py
cherab/imas/ggd/__init__.py
cherab/imas/ggd/unstruct_2d_extend_mesh.py
cherab/imas/wall/wall.py
cherab/imas/wall/__init__.py
cherab/imas/datasets/_fetchers.py
cherab/imas/datasets/__init__.py
cherab/imas/datasets/_registry.py
cherab/imas/datasets/_progress.py
cherab/imas/datasets/_utils.py
cherab/imas/observer/bolometer.py
cherab/imas/observer/__init__.py
cherab/imas/math/tetrahedralize.cpython-310-darwin.so
cherab/imas/math/tetrahedralize.pyi
cherab/imas/math/__init__.pxd
cherab/imas/math/tetrahedralize.cpython-311-darwin.so
cherab/imas/math/__init__.py
cherab/imas/math/functions/__init__.pxd
cherab/imas/math/functions/__init__.py
cherab/imas/math/functions/vector_functions.pyi
cherab/imas/math/functions/vector_functions.cpython-311-darwin.so
cherab/imas/math/functions/vector_functions.pxd
cherab/imas/math/functions/vector_functions.cpython-310-darwin.so
cherab/imas/math/interpolators/unstruct_grid_2d_functions.cpython-311-darwin.so
cherab/imas/math/interpolators/struct_grid_3d_functions.pxd
cherab/imas/math/interpolators/struct_grid_2d_functions.cpython-310-darwin.so
cherab/imas/math/interpolators/struct_grid_2d_functions.pxd
cherab/imas/math/interpolators/__init__.pxd
cherab/imas/math/interpolators/unstruct_grid_2d_functions.cpython-310-darwin.so
cherab/imas/math/interpolators/struct_grid_2d_functions.pyi
cherab/imas/math/interpolators/struct_grid_2d_functions.cpython-311-darwin.so
cherab/imas/math/interpolators/__init__.py
cherab/imas/math/interpolators/struct_grid_3d_functions.pyi
cherab/imas/math/interpolators/struct_grid_3d_functions.cpython-310-darwin.so
