Metadata-Version: 2.4
Name: cherab-imas
Version: 0.3.0
Summary: Cherab spectroscopy framework: IMAS submodule
Author: vsnever, jacklovell
Author-email: munechika-koyo <munechika.koyo@gmail.com>
License-Expression: EUPL-1.1
License-File: LICENCE.txt
Keywords: IMAS,cherab,fusion,imas,plasma,tokamak
Classifier: Development Status :: 4 - Beta
Classifier: Intended Audience :: Developers
Classifier: Intended Audience :: Education
Classifier: Intended Audience :: Science/Research
Classifier: Natural Language :: English
Classifier: Operating System :: Unix
Classifier: Programming Language :: Cython
Classifier: Programming Language :: Python :: 3.10
Classifier: Programming Language :: Python :: 3.11
Classifier: Programming Language :: Python :: 3.12
Classifier: Topic :: Scientific/Engineering :: Physics
Classifier: Topic :: Software Development :: Libraries
Classifier: Topic :: Software Development :: Libraries :: Python Modules
Requires-Python: >=3.10
Requires-Dist: cherab==1.5.*
Requires-Dist: imas-python[netcdf]
Requires-Dist: typing-extensions; python_version < '3.12'
Provides-Extra: test
Requires-Dist: pooch; extra == 'test'
Requires-Dist: pytest; extra == 'test'
Requires-Dist: pytest-cov; extra == 'test'
Requires-Dist: rich; extra == 'test'
